{
  "links": [
    {
      "href": "https://landsatlook.usgs.gov/stac-server/collections/landsat-c2ard-bt/items",
      "rel": "items"
    },
    {
      "href": "https://landsatlook.usgs.gov/stac-server/collections/landsat-c2ard-bt",
      "rel": "canonical"
    },
    {
      "href": "../catalog.json",
      "rel": "parent"
    },
    {
      "href": "../../catalog.json",
      "rel": "root"
    },
    {
      "href": "./LC09_AK_006013_20241103_20241107_02_BT.json",
      "rel": "item"
    }
  ],
  "heystac:cumulative_rating": 1,
  "heystac:total": 1,
  "heystac:cumulative_total": 2,
  "heystac:stars": 2.5,
  "heystac:checks": [
    {
      "name": "validate-core",
      "rating": 0,
      "total": 1,
      "message": "Validation failed for Collection with ID landsat-c2ard-bt against schema at https://schemas.stacspec.org/v1.0.0/collection-spec/json-schema/collection.json\n'https://d9-wret.s3.us-west-2.amazonaws.com/assets/palladium/production/s3fs-public/atoms/files/Landsat_Data_Policy.pdf' does not match '^[\\\\w\\\\-\\\\.\\\\+]+$'\n\nFailed validating 'pattern' in schema['allOf'][0]['properties']['license']:\n    {'title': 'Collection License Name',\n     'type': 'string',\n     'pattern': '^[\\\\w\\\\-\\\\.\\\\+]+$'}\n\nOn instance['license']:\n    'https://d9-wret.s3.us-west-2.amazonaws.com/assets/palladium/production/s3fs-public/atoms/files/Landsat_Data_Policy.pdf'"
    }
  ],
  "type": "Collection",
  "id": "landsat-c2ard-bt",
  "heystac:rating": 0,
  "stac_version": "1.0.0",
  "stac_extensions": [
    "https://stac-extensions.github.io/view/v1.0.0/schema.json",
    "https://stac-extensions.github.io/item-assets/v1.0.0/schema.json"
  ],
  "title": "Landsat Collection 2 Analysis Ready Data (ARD) Level-2 UTM Top of Atmosphere Brightness Temperature (BT) Product",
  "description": "The Landsat Top of Atmosphere Brightness Temperature (BT) product is a top of atmosphere product with radiance calculated 'at-sensor', not atmospherically corrected, and expressed in units of Kelvin.",
  "keywords": [
    "landsat",
    "landsat 4",
    "landsat 5",
    "landsat 7",
    "landsat 8",
    "landsat 9",
    "analysis ready data",
    "top of atmosphere brightness temperature"
  ],
  "extent": {
    "spatial": {
      "bbox": [
        [
          -180,
          -90,
          180,
          90
        ]
      ]
    },
    "temporal": {
      "interval": [
        [
          "1982-08-22T00:00:00.000Z",
          null
        ]
      ]
    }
  },
  "providers": [
    {
      "name": "U.S. Geological Survey (USGS) Earth Resources Observation and Science (EROS) Center",
      "roles": [
        "producer",
        "processor",
        "host"
      ],
      "url": "https://eros.usgs.gov/"
    }
  ],
  "license": "https://d9-wret.s3.us-west-2.amazonaws.com/assets/palladium/production/s3fs-public/atoms/files/Landsat_Data_Policy.pdf",
  "summaries": {
    "platform": [
      "LANDSAT_4",
      "LANDSAT_5",
      "LANDSAT_7",
      "LANDSAT_8",
      "LANDSAT_9"
    ],
    "view:off_nadir": {
      "minimum": 0,
      "maximum": 90
    }
  },
  "item_assets": {}
}